platypus/__init__.py
platypus/__main__.py
platypus/_math.py
platypus/_tools.py
platypus/algorithms.py
platypus/config.py
platypus/core.py
platypus/deprecated.py
platypus/distance.py
platypus/errors.py
platypus/evaluator.py
platypus/experimenter.py
platypus/extensions.py
platypus/filters.py
platypus/indicators.py
platypus/io.py
platypus/mpipool.py
platypus/operators.py
platypus/problems.py
platypus/types.py
platypus/weights.py
platypus/tests/__init__.py
platypus/tests/_utils.py
platypus/tests/test_algorithms.py
platypus/tests/test_config.py
platypus/tests/test_core.py
platypus/tests/test_distance.py
platypus/tests/test_filters.py
platypus/tests/test_indicators.py
platypus/tests/test_io.py
platypus/tests/test_main.py
platypus/tests/test_math.py
platypus/tests/test_operators.py
platypus/tests/test_problems.py
platypus/tests/test_tools.py
platypus/tests/test_types.py
Platypus_Opt-1.4.1.dist-info/COPYING
Platypus_Opt-1.4.1.dist-info/METADATA
Platypus_Opt-1.4.1.dist-info/WHEEL
Platypus_Opt-1.4.1.dist-info/entry_points.txt
Platypus_Opt-1.4.1.dist-info/top_level.txt
Platypus_Opt-1.4.1.dist-info/RECORD
