Metadata-Version: 2.1
Name: Platypus-Opt
Version: 1.4.1
Summary: Multiobjective optimization in Python
Author-email: David Hadka <dhadka@users.noreply.github.com>
License:                     GNU GENERAL PUBLIC LICENSE
Project-URL: Homepage, https://github.com/Project-Platypus/Platypus
Project-URL: Documentation, https://platypus.readthedocs.io/
Project-URL: Bug Tracker, https://github.com/Project-Platypus/Platypus/issues
Requires-Python: >=3.8
License-File: COPYING
Provides-Extra: test
Requires-Dist: pytest; extra == "test"
Requires-Dist: mock; extra == "test"
Requires-Dist: flake8; extra == "test"
Requires-Dist: flake8-pyproject; extra == "test"
Requires-Dist: numpy; extra == "test"
Requires-Dist: matplotlib; extra == "test"
Requires-Dist: jsonpickle; extra == "test"
Provides-Extra: docs
Requires-Dist: sphinx; extra == "docs"
Requires-Dist: sphinx-rtd-theme; extra == "docs"
Provides-Extra: full
Requires-Dist: mpi4py; extra == "full"
Requires-Dist: Platypus-Opt[test]; extra == "full"
Requires-Dist: Platypus-Opt[docs]; extra == "full"
